py_bing_search/__init__.py
py_bing_search/py_bing_search.py
py_bing_search-0.2.6.dist-info/DESCRIPTION.rst
py_bing_search-0.2.6.dist-info/METADATA
py_bing_search-0.2.6.dist-info/RECORD
py_bing_search-0.2.6.dist-info/WHEEL
py_bing_search-0.2.6.dist-info/metadata.json
py_bing_search-0.2.6.dist-info/top_level.txt
tests/__init__.py
tests/test_py_bing_search.py
