Metadata-Version: 2.0
Name: py-bing-search
Version: 0.2.6
Summary: A simple lightweight python wrapper for the Azure Bing Search API.
Home-page: https://github.com/tristantao/py-bing-search
Author: Tristan Tao
Author-email: tristan@teamleada.com
License: MIT
Keywords: Azure,Bing,API,Search
Platform: UNKNOWN
Classifier: Development Status :: 4 - Beta
Classifier: Intended Audience :: Developers
Classifier: License :: OSI Approved :: MIT License
Classifier: Operating System :: OS Independent
Classifier: Programming Language :: Python
Classifier: Programming Language :: Python :: 2
Classifier: Programming Language :: Python :: 3
Classifier: Topic :: Software Development :: Libraries :: Python Modules
Requires-Dist: requests
